Direct_Downloader-0.7.data/scripts/__main__.py
Direct_Downloader-0.7.data/scripts/direct_downloader.py
Direct_Downloader-0.7.dist-info/DESCRIPTION.rst
Direct_Downloader-0.7.dist-info/METADATA
Direct_Downloader-0.7.dist-info/RECORD
Direct_Downloader-0.7.dist-info/WHEEL
Direct_Downloader-0.7.dist-info/entry_points.txt
Direct_Downloader-0.7.dist-info/metadata.json
Direct_Downloader-0.7.dist-info/top_level.txt
directdownloader/__init__.py
directdownloader/__main__.py
directdownloader/direct_downloader.py
