Metadata-Version: 2.0
Name: Direct-Downloader
Version: 0.7
Summary: Download a list of direct links using multi-threading.
Home-page: https://github.com/santosderek/Direct-Downloader
Author: Derek Santos
Author-email: derek@dyrenex.com
License: The MIT License (MIT)
Keywords: testing,logging,example
Platform: UNKNOWN
Requires-Dist: bs4
Requires-Dist: requests
